daisy_mkdocs/404.html
daisy_mkdocs/__init__.py
daisy_mkdocs/components/collapse.html
daisy_mkdocs/components/menu.html
daisy_mkdocs/components/steps.html
daisy_mkdocs/components/table.html
daisy_mkdocs/content.html
daisy_mkdocs/header.html
daisy_mkdocs/input.css
daisy_mkdocs/main.html
daisy_mkdocs/sidebar.html
daisy_mkdocs/styles.css
daisy_mkdocs/templates/endpoint.html
daisy_mkdocs-0.1.2.dist-info/METADATA
daisy_mkdocs-0.1.2.dist-info/WHEEL
daisy_mkdocs-0.1.2.dist-info/entry_points.txt
daisy_mkdocs-0.1.2.dist-info/RECORD
