Metadata-Version: 2.1
Name: daisy-mkdocs
Version: 0.1.2
Summary: 
Author: karl robeck alferez
Author-email: karlalferezfx@gmail.com
Requires-Python: >=3.12,<4.0
Classifier: Programming Language :: Python :: 3
Classifier: Programming Language :: Python :: 3.12
Requires-Dist: mkdocs (>=1.5.3,<2.0.0)
Requires-Dist: pymdown-extensions (>=10.7,<11.0)
